opticlient/__init__.py
opticlient/client.py
opticlient/config.py
opticlient/http.py
opticlient/models/__init__.py
opticlient/models/jobs.py
opticlient/tools/__init__.py
opticlient/tools/base.py
opticlient/tools/sms.py
opticlient/tools/sms_parser.py
opticlient/utils/__init__.py
opticlient/utils/ziptools.py
opticlient-0.1.2.dist-info/METADATA
opticlient-0.1.2.dist-info/WHEEL
opticlient-0.1.2.dist-info/licenses/LICENSE
opticlient-0.1.2.dist-info/RECORD
