Metadata-Version: 2.4
Name: opticlient
Version: 0.1.2
Summary: Python client for SaaS optimization API
Project-URL: Homepage, https://cad-eta.vercel.app
Project-URL: Source, https://github.com/Milan-Adhikari/opticlient
Author-email: Milan Adhikari <reach.out.to.milan@gmail.com>
License: MIT
License-File: LICENSE
Requires-Python: >=3.9
Requires-Dist: httpx>=0.27.0
Provides-Extra: dev
Requires-Dist: build; extra == 'dev'
Requires-Dist: pytest; extra == 'dev'
Requires-Dist: twine; extra == 'dev'
